preprintscout/__init__.py
preprintscout/arxiv_articles.py
preprintscout/embedding.py
preprintscout/llms.py
preprintscout/osf_articles.py
preprintscout/philarchive_articles.py
preprintscout/pps.py
preprintscout/py_error_log.txt
preprintscout/requirements.txt
preprintscout/resources/arxiv_taxonomy.csv
preprintscout/resources/discipline_dissimilarity_matrix.csv
preprintscout/resources/schema_mapping_cleaned.csv
preprintscout-0.1.4.dist-info/METADATA
preprintscout-0.1.4.dist-info/WHEEL
preprintscout-0.1.4.dist-info/licenses/LICENSE
preprintscout-0.1.4.dist-info/RECORD
