Metadata-Version: 2.3
Name: preprintscout
Version: 0.1.4
Summary: Preprint article recommender
Project-URL: Homepage, https://github.com/ryanrwatkins/preprints_recommender
Author: Ryan Watkins
License: MIT
License-File: LICENSE
Classifier: License :: OSI Approved :: MIT License
Classifier: Operating System :: OS Independent
Classifier: Programming Language :: Python :: 3
Requires-Dist: arxiv>=2.1.3
Requires-Dist: beautifulsoup4>=4.12.3
Requires-Dist: google-generativeai>=0.7.0
Requires-Dist: langdetect>=1.0.9
Requires-Dist: openai>=1.35.7
Requires-Dist: pandas>=2.2.2
Requires-Dist: pytz>=2024.1
Requires-Dist: requests>=2.32.3
Requires-Dist: retry>=0.9.2
Requires-Dist: scikit-learn>=1.4.2
